scrapy_rabbitmq_publisher/__init__.py
scrapy_rabbitmq_publisher/pipelines.py
scrapy_rabbitmq_publisher-0.1.4.dist-info/LICENSE
scrapy_rabbitmq_publisher-0.1.4.dist-info/METADATA
scrapy_rabbitmq_publisher-0.1.4.dist-info/WHEEL
scrapy_rabbitmq_publisher-0.1.4.dist-info/top_level.txt
scrapy_rabbitmq_publisher-0.1.4.dist-info/RECORD
