Metadata-Version: 2.1
Name: scrapy-rabbitmq-publisher
Version: 0.1.4
Summary: Scrapy Item Pipeline to send items to RabbitMQ
Home-page: https://github.com/artemrys/scrapy-rabbitmq-publisher
Author: Artem Rys
Author-email: rysartem@gmail.com
License: MIT
Platform: UNKNOWN
Requires-Dist: pika
Requires-Dist: Scrapy (>=0.14)
